{
    "anytime" : [
        "Ce sexy ești!",
        "Sunt norocoasă să fiu oglinda ta!",
        "Ai ochi frumoși!",
        "Arăți perfect!",
        "Ai un zâmbet minunat. Zâmbește!",
        "Ești ca o gură de aer proaspăt"
    ],
    "morning" : [
        "Bună dimineața!",
        "Astăzi ai un zâmbet minunat!",
        "Să ai o zi minunată!",
        "Cum ai dormit?",
        "Astăzi vei avea numai bucurii",
        "Pregătește-te: vei avea o zi frumoasă!"
    ],
    "afternoon" : [
        "Tu faci diferența astăzi!",
        "Bună, frumusețe!",
        "Arăți bine astăzi!"
    ],
    "evening" : [
        "Știu că astăzi ai făcut pe cineva să zâmbească",
        "Ziua a fost mai bună datorită ție",
        "Somn ușor"
    ],
    "snow": [
        "Ninge!"
    ],
    "day_sunny" : [
        "E o zi frumoasă afară"
    ],
    "day_cloudy" : [
        "Soarele e ascuns in nori"
    ],
    "cloudy" : [
    ],
    "cloudy_windy" : [
    ],
    "showers" : [
        "Plouă, nu uita umbrela!",
        "Ești ca soarele într-o zi ploioasă"
    ],
    "rain" : [
        "Plouă, nu uita umbrela!",
        "Plouă, dar tu înveselești ziua oricui!",
        "Ești ca soarele într-o zi ploioasă"
    ],
    "thunderstorm" : [
    ],
    "fog" : [
        "Este ceață  afară",
        "Ești ca soarele într-o zi cu ceață"
    ],
    "night_clear": [
        "Noaptea asta e senin",
        "Ne vedem dimineață!"
    ],
    "night_cloudy" : [
        "E cam innorat  afară",
        "Ne vedem dimineață!"
    ],
    "night_showers" : [
        "Ne vedem dimineață!"
    ],
    "night_rain" : [
        "Noaptea asta plouă",
        "Ne vedem dimineață!"
    ],
    "night_thunderstorm" : [
        "Noaptea asta e furtună afară",
        "Ne vedem dimineață!"
    ],
    "night_alt_cloudy_windy" : [
        "Ne vedem dimineață!"
    ],
    "....-01-01": [
        "La mulți ani!"
    ],
    "....-12-25": [
        "Crăciun fericit!"
    ]
}
